{
  "upazilas": [
    {
      "id": "13221",
      "district_id": "132",
      "name": "Fulchhari"
    },
    {
      "id": "13288",
      "district_id": "132",
      "name": "Saghata"
    },
    {
      "id": "13291",
      "district_id": "132",
      "name": "Sundarganj"
    },
    {
      "id": "13907",
      "district_id": "139",
      "name": "Ajmiriganj"
    },
    {
      "id": "13929",
      "district_id": "139",
      "name": "Baniachong"
    },
    {
      "id": "14908",
      "district_id": "149",
      "name": "Bakshiganj"
    },
    {
      "id": "14918",
      "district_id": "149",
      "name": "Islampur"
    },
    {
      "id": "14961",
      "district_id": "149",
      "name": "Austagram"
    },
    {
      "id": "14977",
      "district_id": "149",
      "name": "Itna"
    },
    {
      "id": "18811",
      "district_id": "188",
      "name": "Mithamain"
    },
    {
      "id": "18827",
      "district_id": "188",
      "name": "Nikli"
    },
    {
      "id": "18867",
      "district_id": "188",
      "name": "Char Rajibpur"
    },
    {
      "id": "23602",
      "district_id": "236",
      "name": "Nageshwari"
    },
    {
      "id": "23611",
      "district_id": "236",
      "name": "Phulbari"
    },
    {
      "id": "24802",
      "district_id": "248",
      "name": "Rajarhat"
    },
    {
      "id": "24833",
      "district_id": "248",
      "name": "Kalmakanda"
    },
    {
      "id": "24859",
      "district_id": "248",
      "name": "Khaliajuri"
    },
    {
      "id": "24876",
      "district_id": "248",
      "name": "Madan"
    },
    {
      "id": "27238",
      "district_id": "272",
      "name": "Belkuchi"
    },
    {
      "id": "27240",
      "district_id": "272",
      "name": "Chauhali"
    },
    {
      "id": "27256",
      "district_id": "272",
      "name": "Shahjadpur"
    },
    {
      "id": "29033",
      "district_id": "290",
      "name": "Dowarabazar"
    },
    {
      "id": "29092",
      "district_id": "290",
      "name": "Tahirpur"
    }
  ]
}